[
  {
    "title": "The Mathews",
    "credit": "credit2",
    "link": "https://youtu.be/R3WEqF1NGFM?t=63"
  },
  {
    "title": "La Croquetta",
    "credit": "credit4",
    "link": "https://youtu.be/9lu6YJ7yZHc?t=264"
  },
  {
    "title": "Cruyff Turn",
    "credit": "credit4",
    "link": "https://youtu.be/9lu6YJ7yZHc?t=41"
  },
  {
    "title": "Drag Back Croquetta",
    "credit": "credit1",
    "link": "https://youtu.be/qCtycLYicL8?t=181"
  },
  {
    "title": "The Stop And Start",
    "credit": "credit2",
    "link": "https://youtu.be/R3WEqF1NGFM?t=188"
  },
  {
    "title": "Double Elastico",
    "credit": "credit4",
    "link": "https://youtu.be/JKipMJfaf6E?t=63"
  },
  {
    "title": "The Stepover",
    "credit": "credit2",
    "link": "https://youtu.be/R3WEqF1NGFM?t=40"
  },
  {
    "title": "Drag Back",
    "credit": "credit1",
    "link": "null"
  },
  {
    "title": "Isco V-Drag",
    "credit": "credit1",
    "link": "https://youtu.be/qCtycLYicL8?t=79"
  },
  {
    "title": "Stepover La Croquetta",
    "credit": "credit2",
    "link": "https://youtu.be/R3WEqF1NGFM?t=153"
  },
  {
    "title": "Forward McGeady",
    "credit": "credit4",
    "link": "https://youtu.be/JKipMJfaf6E?t=101"
  },
  {
    "title": "Outside Inside",
    "credit": "credit2",
    "link": "null"
  },
  {
    "title": "The Roll",
    "credit": "credit1",
    "link": "null"
  },
  {
    "title": "Isco Mesmerizer",
    "credit": "credit1",
    "link": "https://youtu.be/qCtycLYicL8?t=181"
  },
  {
    "title": "The Elastico",
    "credit": "credit2",
    "link": "https://youtu.be/R3WEqF1NGFM?t=99"
  },
  {
    "title": "Stepover Turn",
    "credit": "credit1",
    "link": "null"
  },
  {
    "title": "Self Pass",
    "credit": "credit2",
    "link": "https://youtu.be/R3WEqF1NGFM?t=130"
  },
  {
    "title": "Roll Top Chop",
    "credit": "credit4",
    "link": "https://youtu.be/JKipMJfaf6E?t=169"
  },
  {
    "title": "The Roulette",
    "credit": "credit2",
    "link": "null"
  },
  {
    "title": "Reverse Elastico",
    "credit": "credit4",
    "link": "https://youtu.be/JKipMJfaf6E?t=322"
  },
  {
    "title": "Roll Top Stepover",
    "credit": "credit4",
    "link": "https://youtu.be/JKipMJfaf6E?t=513"
  },
  {
    "title": "Hocus Pocus",
    "credit": "credit4",
    "link": "https://youtu.be/JKipMJfaf6E?t=287"
  },
  {
    "title": "Inside To Inside",
    "credit": "credit4",
    "link": "https://youtu.be/JKipMJfaf6E?t=461"
  },
  {
    "title": "The Fakeshot",
    "credit": "credit2",
    "link": "null"
  },
  {
    "title": "The Chop",
    "credit": "credit2",
    "link": "null"
  },
  {
    "title": "Body Feint",
    "credit": "credit2",
    "link": "https://youtu.be/R3WEqF1NGFM?t=213"
  },
  {
    "title": "Fake Rabona",
    "credit": "credit4",
    "link": "null"
  },
  {
    "title": "Drag N' Stepover",
    "credit": "credit4",
    "link": "https://youtu.be/JKipMJfaf6E?t=256"
  },
  {
    "title": "Double Stepover",
    "credit": "credit2",
    "link": "null"
  },
  {
    "title": "Blanco",
    "credit": "credit4",
    "link": "https://youtu.be/JKipMJfaf6E?t=136"
  },
  {
    "title": "Sombrero",
    "credit": "credit4",
    "link": "https://youtu.be/JKipMJfaf6E?t=206"
  },
  {
    "title": "Side Skip",
    "credit": "credit2",
    "link": "https://youtu.be/R3WEqF1NGFM?t=240"
  },
  {
    "title": "Roll To Heel",
    "credit": "credit4",
    "link": "https://youtu.be/JKipMJfaf6E?t=485"
  },
  {
    "title": "Chop Outside Cut",
    "credit": "credit2",
    "link": "https://youtu.be/R3WEqF1NGFM?t=299"
  },
  {
    "title": "",
    "credit": "credit1",
    "link": "null"
  },
  {
    "title": "Rainbow",
    "credit": "credit2"
  },
  {
    "title": "Rainbow II",
    "credit": "credit2"
  }
]